{
  "slug": "dragonforce-hughes-atwood-mullaly-pllc-2026-07-15",
  "title": "Hughes Atwood & Mullaly pllc",
  "group": "dragonforce",
  "discovered": "2026-07-15T12:55:27.000Z",
  "category": "ransomware",
  "severity": "critical",
  "country": "US",
  "sizeBytes": 0,
  "description": "Status: data_published",
  "source_url": "https://darkfield.orizon.one/victims/dd501e9c-6a6a-456c-972c-0a8339d0b499",
  "groupAliases": ["DRAGON FORCE"],
  "activity": "Business Services",
  "references": ["Darkfield"]
}
