{"slug":"everest-tsys-2026-05-02","title":"TSYS","group":"everest","discovered":"2026-05-02T03:54:24.000Z","category":"ransomware","severity":"critical","country":"US","sizeBytes":0,"description":"[AI generated] TSYS, or Total System Services, is a US-based payment solutions company headquartered in Columbus, Georgia. It operates in the financial technology and payment processing industry, providing services such as credit and debit card processing, merchant services, and payment management solutions to financial institutions, businesses, and consumers worldwide. TSYS became a subsidiary of Global Payments following a merger in 2019.","source_url":"https://www.ransomware.live/","groupAliases":[],"activity":"Financial Services","references":["ransomware.live"]}