{"slug":"fulcrumsec-mco-2026-05-01","title":"MCO","group":"fulcrumsec","discovered":"2026-05-01T17:08:05.000Z","category":"ransomware","severity":"high","country":"US","sizeBytes":0,"description":"[AI generated] N/A\n\nThe acronym \"MCO\" is too ambiguous to identify a specific company with confidence. Multiple organizations share this abbreviation across different industries and countries. Please provide additional context such as the full company name, industry, or country of operation to allow for an accurate and reliable description.","source_url":"https://www.ransomware.live/","groupAliases":[],"activity":"Financial Services","references":["ransomware.live"]}