{"slug":"leakbazaar-e-jones-associates-lcc-2026-05-10","title":"e-jones associates LCC","group":"LeakBazaar","discovered":"2026-05-10T08:58:03.000Z","category":"data_breach","severity":"high","country":"US","sizeBytes":0,"description":"Here are E. Jones & Associates, LLC, our focus is on our clients at all times. We only work on personal filings, leaving the commercial sector to other Atlanta bankruptcy law firms. Each person who comes into our office receives our undivided attention, and our clients benefit from our specialized knowledge and experience. We have an intimate knowledge of our business. We have a thorough understanding of not only the ins and outs of Atlanta bankruptcy filing, but also the needs of our clients. We have seen it all: lost jobs, health issues, divorce. We know how people can feel during trying times such as these. E. Jones & Associates, LLC is the compass pointing to financial freedom. We are with you every step of the way. Our Atlanta Bankruptcy lawyers will advise and direct you through each part of the process, leaving nothing for speculation. We provide you with an exit from your troubles, putting you on the road to financial security.\n\nThere are 2,400 unique clients of the law firm in total.\n\nYou can purchase both the entire data and the data of individual clients for a price starting from $100. The full list of clients is in the attachment.","source_url":"https://www.ransomware.live/","groupAliases":["leak bazaar"],"activity":"Professional Services","references":["ransomware.live"]}