{"slug":"nova-badan-pangan-nasional-2026-05-29","title":"Badan Pangan Nasional","group":"nova","discovered":"2026-05-29T13:53:31.000Z","category":"ransomware","severity":"high","country":"ID","sizeBytes":0,"description":"Badan Pangan Nasional is an Indonesian government agency focused on ensuring food security and stability in the country. It provides services related to food supply, pricing, and consumption, while also addressing issues of food safety and nutrition. The agency aims to support national food sovereignty through various programs and initiatives, targeting local communities and stakeholders in the agricultural sector. Additionally, it engages in public information services to enhance transparency and accessibility regarding food-related regulations and data - Nova Provide tree and samples from stolen data to the company when its get in touch with support department.","source_url":"https://www.ransomware.live/","groupAliases":[],"activity":"Agriculture and Food Production","references":["ransomware.live"]}