{"slug":"space-bears-doalltech-2026-07-22","title":"DoAllTech","group":"space bears","discovered":"2026-07-22T06:21:09.000Z","category":"data_breach","severity":"high","country":null,"sizeBytes":0,"description":"The Company is leading the construction IT industry with the best technology and various experiences, and striving to grow with a various customers in pursuit of technology platform change and innovation through persistent research and development in introduction of Web Services, H/W Services, BIM Services, and new technologies.-Personal information of employees and clients\n-Financial\ndocuments\n-Other files\nhttps://doalltech.com/en/","source_url":"https://www.ransomlook.io/screenshots/space bears/DoAllTech.png","groupAliases":[],"activity":null,"references":["ransomlook.io"]}