{"slug":"thegentlemen-carita-2026-07-11","title":"Carita","group":"thegentlemen","discovered":"2026-07-11T07:18:11.000Z","category":"ransomware","severity":"critical","country":"FR","sizeBytes":0,"description":"***.com zoominfo.com/c/carita/358348689 Carita is a prestigious French luxury skincare brand founded in 1945, renowned for its professional-grade beauty treatments and high-end cosmetics. Now part of L'Oréal's Luxury Division following its acquisition from Shiseido in 2022, the brand operates globally with a focus on exceptional skincare rituals and personalized beauty experiences. Available in over 130 countries, Carita combines innovative formulations with artisanal expertise, generating annual revenue in the range of $9-10 million for its core operations","source_url":"https://www.ransomware.live/","groupAliases":["the gentlemen"],"activity":"Retail & E-Commerce","references":["ransomware.live"]}